dodi/README.md
dodi/RELEASE_NOTES.md
dodi/VERSION
dodi/__init__.py
dodi/_etag_responder.py
dodi/_operations.py
dodi/_respond_with_e_tag.py
dodi/_utils.py
dodi/_views.py
dodi/py.typed
dodi/transform.py
dodi/urls.py
dodi/validator.py
dodi/__pycache__/__init__.cpython-36.pyc
dodi/__pycache__/__init__.cpython-39.pyc
dodi/__pycache__/_etag_responder.cpython-36.pyc
dodi/__pycache__/_etag_responder.cpython-39.pyc
dodi/__pycache__/_exceptions.cpython-36.pyc
dodi/__pycache__/_operations.cpython-36.pyc
dodi/__pycache__/_operations.cpython-39.pyc
dodi/__pycache__/_respond_with_e_tag.cpython-39.pyc
dodi/__pycache__/_transform.cpython-36.pyc
dodi/__pycache__/_utils.cpython-36.pyc
dodi/__pycache__/_utils.cpython-39.pyc
dodi/__pycache__/_views.cpython-36.pyc
dodi/__pycache__/_views.cpython-39.pyc
dodi/__pycache__/transform.cpython-36.pyc
dodi/__pycache__/transform.cpython-39.pyc
dodi/__pycache__/urls.cpython-36.pyc
dodi/__pycache__/urls.cpython-39.pyc
dodi/__pycache__/validator.cpython-36.pyc
dodi/__pycache__/validator.cpython-39.pyc
dodi-2.5.0.dist-info/LICENSE
dodi-2.5.0.dist-info/METADATA
dodi-2.5.0.dist-info/WHEEL
dodi-2.5.0.dist-info/top_level.txt
dodi-2.5.0.dist-info/RECORD
