Metadata-Version: 2.1
Name: dodi
Version: 2.5.0
Summary: Django On-Demand Images
Author: Alex Fischer
Author-email: alex@quadrant.net
Classifier: Programming Language :: Python :: 3
Classifier: License :: OSI Approved :: MIT License
Classifier: Operating System :: OS Independent
Requires-Python: >=3.7
License-File: LICENSE
Requires-Dist: Django <6,>=3
Requires-Dist: Pillow <12,>=9
